  {
   "type": "folder",
   "name": "Google",
   "path": "C:\\Program Files (x86)\\Google",
   "childno": 1,
   "subchilds": 5,
   "children": [
    {
     "type": "folder",
     "name": "Chrome Remote Desktop",
     "path": "C:\\Program Files (x86)\\Google\\Chrome Remote Desktop\\Chrome Remote Desktop",
     "childno": 5,
     "subchilds": 2,
     "children": [
      {
       "type": "folder",
       "name": "125.0.6422.6",
       "path": "C:\\Program Files (x86)\\Google\\Chrome Remote Desktop\\125.0.6422.6\\125.0.6422.6",
       "childno": 2,
       "subchilds": 0
      },
      {
       "type": "folder",
       "name": "CurrentVersion",
       "path": "C:\\Program Files (x86)\\Google\\Chrome Remote Desktop\\CurrentVersion\\CurrentVersion",
       "childno": 1,
       "subchilds": 0
      }
     ]
    },
    {
     "type": "folder",
     "name": "CrashReports",
     "path": "C:\\Program Files (x86)\\Google\\CrashReports\\CrashReports",
     "childno": 4,
     "subchilds": 0
    },
    {
     "type": "folder",
     "name": "GoogleUpdater",
     "path": "C:\\Program Files (x86)\\Google\\GoogleUpdater\\GoogleUpdater",
     "childno": 3,
     "subchilds": 1,
     "children": [
      {
       "type": "folder",
       "name": "126.0.6441.0",
       "path": "C:\\Program Files (x86)\\Google\\GoogleUpdater\\126.0.6441.0\\126.0.6441.0",
       "childno": 1,
       "subchilds": 1,
       "children": [
        {
         "type": "folder",
         "name": "Crashpad",
         "path": "C:\\Program Files (x86)\\Google\\GoogleUpdater\\126.0.6441.0\\Crashpad\\Crashpad",
         "childno": 1,
         "subchilds": 2,
         "children": [
          {
           "type": "folder",
           "name": "attachments",
           "path": "C:\\Program Files (x86)\\Google\\GoogleUpdater\\126.0.6441.0\\Crashpad\\attachments\\attachments",
           "childno": 2,
           "subchilds": 0
          },
          {
           "type": "folder",
           "name": "reports",
           "path": "C:\\Program Files (x86)\\Google\\GoogleUpdater\\126.0.6441.0\\Crashpad\\reports\\reports",
           "childno": 1,
           "subchilds": 0
          }
         ]
        }
       ]
      }
     ]
    },
    {
     "type": "folder",
     "name": "Temp",
     "path": "C:\\Program Files (x86)\\Google\\Temp\\Temp",
     "childno": 2,
     "subchilds": 0
    },
    {
     "type": "folder",
     "name": "Update",
     "path": "C:\\Program Files (x86)\\Google\\Update\\Update",
     "childno": 1,
     "subchilds": 0
    }
   ]
  }
